castellan_ui/__init__.py
castellan_ui/karma.conf.js
castellan_ui/version.py
castellan_ui/api/__init__.py
castellan_ui/api/client.py
castellan_ui/content/__init__.py
castellan_ui/content/filters.py
castellan_ui/content/shared_forms.py
castellan_ui/content/opaque_data/__init__.py
castellan_ui/content/opaque_data/forms.py
castellan_ui/content/opaque_data/panel.py
castellan_ui/content/opaque_data/tables.py
castellan_ui/content/opaque_data/urls.py
castellan_ui/content/opaque_data/views.py
castellan_ui/content/passphrases/__init__.py
castellan_ui/content/passphrases/forms.py
castellan_ui/content/passphrases/panel.py
castellan_ui/content/passphrases/tables.py
castellan_ui/content/passphrases/urls.py
castellan_ui/content/passphrases/views.py
castellan_ui/content/private_keys/__init__.py
castellan_ui/content/private_keys/forms.py
castellan_ui/content/private_keys/panel.py
castellan_ui/content/private_keys/tables.py
castellan_ui/content/private_keys/urls.py
castellan_ui/content/private_keys/views.py
castellan_ui/content/public_keys/__init__.py
castellan_ui/content/public_keys/forms.py
castellan_ui/content/public_keys/panel.py
castellan_ui/content/public_keys/tables.py
castellan_ui/content/public_keys/urls.py
castellan_ui/content/public_keys/views.py
castellan_ui/content/symmetric_keys/__init__.py
castellan_ui/content/symmetric_keys/forms.py
castellan_ui/content/symmetric_keys/panel.py
castellan_ui/content/symmetric_keys/tables.py
castellan_ui/content/symmetric_keys/urls.py
castellan_ui/content/symmetric_keys/views.py
castellan_ui/content/x509_certificates/__init__.py
castellan_ui/content/x509_certificates/forms.py
castellan_ui/content/x509_certificates/panel.py
castellan_ui/content/x509_certificates/tables.py
castellan_ui/content/x509_certificates/urls.py
castellan_ui/content/x509_certificates/views.py
castellan_ui/enabled/_90_project_key_manager_panelgroup.py
castellan_ui-0.1.0.dist-info/DESCRIPTION.rst
castellan_ui-0.1.0.dist-info/METADATA
castellan_ui-0.1.0.dist-info/RECORD
castellan_ui-0.1.0.dist-info/WHEEL
castellan_ui-0.1.0.dist-info/metadata.json
castellan_ui-0.1.0.dist-info/pbr.json
castellan_ui-0.1.0.dist-info/top_level.txt
