Metadata-Version: 2.0
Name: castellan-ui
Version: 0.1.0
Summary: Generic Key Manager UI Plugin for Horizon
Home-page: http://www.openstack.org/
Author: OpenStack
Author-email: openstack-dev@lists.openstack.org
License: UNKNOWN
Platform: UNKNOWN
Classifier: Environment :: OpenStack
Classifier: Intended Audience :: Information Technology
Classifier: Intended Audience :: System Administrators
Classifier: License :: OSI Approved :: Apache Software License
Classifier: Operating System :: POSIX :: Linux
Classifier: Programming Language :: Python
Classifier: Programming Language :: Python :: 2
Classifier: Programming Language :: Python :: 2.7
Classifier: Programming Language :: Python :: 3
Classifier: Programming Language :: Python :: 3.4
Requires-Dist: pbr (!=2.1.0,>=2.0.0)
Requires-Dist: Babel (!=2.4.0,>=2.3.4)
Requires-Dist: Django (<2.0,>=1.8)
Requires-Dist: django-babel (>=0.5.1)
Requires-Dist: django-compressor (>=2.0)
Requires-Dist: django-openstack-auth (>=3.5.0)
Requires-Dist: django-pyscss (>=2.0.2)
Requires-Dist: castellan (>=0.7.0)
